binance/__init__.py
binance/core/__init__.py
binance/core/__init__.pyi
binance/core/exc.py
binance/core/mixin.py
binance/core/util.py
binance/core/validation.py
binance/core/http/__init__.py
binance/core/http/__init__.pyi
binance/core/http/auth.py
binance/core/http/client.py
binance/simple_earn/__init__.py
binance/simple_earn/fixed/__init__.py
binance/simple_earn/fixed/list.py
binance/simple_earn/flexible/__init__.py
binance/simple_earn/flexible/list.py
binance/wallet/__init__.py
binance/wallet/capital/__init__.py
binance/wallet/capital/coins.py
typed_binance-0.1.2.dist-info/METADATA
typed_binance-0.1.2.dist-info/WHEEL
typed_binance-0.1.2.dist-info/top_level.txt
typed_binance-0.1.2.dist-info/RECORD
